{
  "info": {
    "description": "Tomato Plant Dataset - Images of tomato plants with bounding box annotations",
    "version": "1.0",
    "year": 2024,
    "contributor": "Tomato Plant Research",
    "date_created": "2025/04/12",
    "url": ""
  },
  "images": [
    {
      "id": 264,
      "license": 1,
      "file_name": "0263.JPG",
      "height": 3024,
      "width": 4032,
      "date_captured": "2025-04-12"
    }
  ],
  "annotations": [
    {
      "id": 4001420473,
      "image_id": 264,
      "category_id": 0,
      "bbox": [
        0.9999360000000068,
        2951.0006399999997,
        133.99948799999999,
        72.99936000000001
      ],
      "area": 9781.87686432768,
      "segmentation": [],
      "iscrowd": 0
    },
    {
      "id": 2986455473,
      "image_id": 264,
      "category_id": 0,
      "bbox": [
        3713.998176,
        954.9988559999999,
        300.00096,
        309.99931200000003
      ],
      "area": 93000.09119933954,
      "segmentation": [],
      "iscrowd": 0
    },
    {
      "id": 7935613473,
      "image_id": 264,
      "category_id": 0,
      "bbox": [
        3666.999168,
        1221.0004800000002,
        361.001088,
        418.001472
      ],
      "area": 150898.98617760153,
      "segmentation": [],
      "iscrowd": 0
    },
    {
      "id": 5182142473,
      "image_id": 264,
      "category_id": 0,
      "bbox": [
        2679.99984,
        2086.99848,
        693.0,
        654.0004799999999
      ],
      "area": 453222.3326399999,
      "segmentation": [],
      "iscrowd": 0
    },
    {
      "id": 2599716473,
      "image_id": 264,
      "category_id": 0,
      "bbox": [
        2891.000448,
        963.99828,
        387.99935999999997,
        353.000592
      ],
      "area": 136964.0037756211,
      "segmentation": [],
      "iscrowd": 0
    },
    {
      "id": 7904346473,
      "image_id": 264,
      "category_id": 0,
      "bbox": [
        65.001888,
        2331.000504,
        337.998528,
        309.001392
      ],
      "area": 104442.01564595099,
      "segmentation": [],
      "iscrowd": 0
    },
    {
      "id": 9239259473,
      "image_id": 264,
      "category_id": 0,
      "bbox": [
        69.00163199999999,
        1171.001664,
        445.99968,
        459.998784
      ],
      "area": 205159.31046438913,
      "segmentation": [],
      "iscrowd": 0
    },
    {
      "id": 9838867473,
      "image_id": 264,
      "category_id": 1,
      "bbox": [
        3070.999008,
        1216.000296,
        550.001088,
        472.00104
      ],
      "area": 259601.0855371315,
      "segmentation": [],
      "iscrowd": 0
    },
    {
      "id": 4954047473,
      "image_id": 264,
      "category_id": 0,
      "bbox": [
        3666.999168,
        2260.000008,
        362.00102400000003,
        417.000528
      ],
      "area": 150954.61814454067,
      "segmentation": [],
      "iscrowd": 0
    },
    {
      "id": 4306176473,
      "image_id": 264,
      "category_id": 0,
      "bbox": [
        0.9999360000000068,
        2481.0014880000003,
        245.000448,
        453.99916799999994
      ],
      "area": 111229.99955162725,
      "segmentation": [],
      "iscrowd": 0
    },
    {
      "id": 3245136473,
      "image_id": 264,
      "category_id": 0,
      "bbox": [
        3305.0001599999996,
        2003.000832,
        570.999744,
        555.000768
      ],
      "area": 316905.2964478034,
      "segmentation": [],
      "iscrowd": 0
    },
    {
      "id": 7849115473,
      "image_id": 264,
      "category_id": 0,
      "bbox": [
        229.99939200000006,
        656.000856,
        584.998848,
        452.00030399999997
      ],
      "area": 264419.65713564976,
      "segmentation": [],
      "iscrowd": 0
    },
    {
      "id": 6584709473,
      "image_id": 264,
      "category_id": 0,
      "bbox": [
        1525.9991040000002,
        1150.001496,
        649.9987199999999,
        536.998896
      ],
      "area": 349048.59504141303,
      "segmentation": [],
      "iscrowd": 0
    },
    {
      "id": 8929434473,
      "image_id": 264,
      "category_id": 0,
      "bbox": [
        2142.999936,
        1200.000312,
        635.999616,
        539.0007840000001
      ],
      "area": 342804.29164769896,
      "segmentation": [],
      "iscrowd": 0
    },
    {
      "id": 8088239473,
      "image_id": 264,
      "category_id": 0,
      "bbox": [
        1.0019519999999948,
        1641.000816,
        572.999616,
        590.000544
      ],
      "area": 338070.08515179105,
      "segmentation": [],
      "iscrowd": 0
    },
    {
      "id": 1081372473,
      "image_id": 264,
      "category_id": 0,
      "bbox": [
        2221.000992,
        1719.0003599999998,
        580.999104,
        574.0005600000001
      ],
      "area": 333493.81105549826,
      "segmentation": [],
      "iscrowd": 0
    },
    {
      "id": 4952494473,
      "image_id": 264,
      "category_id": 0,
      "bbox": [
        226.00166399999995,
        1388.00088,
        907.998336,
        761.999616
      ],
      "area": 691894.3833606389,
      "segmentation": [],
      "iscrowd": 0
    },
    {
      "id": 5199081473,
      "image_id": 264,
      "category_id": 0,
      "bbox": [
        2408.99904,
        543.001536,
        728.001792,
        619.9986240000001
      ],
      "area": 451360.10930953425,
      "segmentation": [],
      "iscrowd": 0
    },
    {
      "id": 2646291473,
      "image_id": 264,
      "category_id": 0,
      "bbox": [
        1424.9995199999998,
        571.000752,
        703.9992960000001,
        674.001216
      ],
      "area": 474496.381567144,
      "segmentation": [],
      "iscrowd": 0
    }
  ],
  "categories": [
    {
      "id": 0,
      "name": "tomato_plant",
      "supercategory": "plant"
    },
    {
      "id": 1,
      "name": "tomato_fruit",
      "supercategory": "fruit"
    }
  ]
}