{
  "info": {
    "description": "Tomato Plant Dataset - Images of tomato plants with bounding box annotations",
    "version": "1.0",
    "year": 2024,
    "contributor": "Tomato Plant Research",
    "date_created": "2025/04/12",
    "url": ""
  },
  "images": [
    {
      "id": 278,
      "license": 1,
      "file_name": "0277.JPG",
      "height": 3024,
      "width": 4032,
      "date_captured": "2025-04-12"
    }
  ],
  "annotations": [
    {
      "id": 5895195473,
      "image_id": 278,
      "category_id": 1,
      "bbox": [
        0.9979199999999978,
        93.00009599999998,
        47.001024,
        177.000768
      ],
      "area": 8319.217344786432,
      "segmentation": [],
      "iscrowd": 0
    },
    {
      "id": 4869736473,
      "image_id": 278,
      "category_id": 0,
      "bbox": [
        905.000544,
        285.001416,
        165.00153600000002,
        184.999248
      ],
      "area": 30525.16007884493,
      "segmentation": [],
      "iscrowd": 0
    },
    {
      "id": 4221232473,
      "image_id": 278,
      "category_id": 1,
      "bbox": [
        3180.0000959999998,
        1495.000584,
        289.001664,
        414.00072
      ],
      "area": 119646.89697719808,
      "segmentation": [],
      "iscrowd": 0
    },
    {
      "id": 7601849473,
      "image_id": 278,
      "category_id": 0,
      "bbox": [
        0.9979200000000048,
        1258.000632,
        175.00089599999998,
        277.999344
      ],
      "area": 48650.13428741222,
      "segmentation": [],
      "iscrowd": 0
    },
    {
      "id": 7366143473,
      "image_id": 278,
      "category_id": 0,
      "bbox": [
        2836.999872,
        1655.999856,
        347.001984,
        293.001408
      ],
      "area": 101672.06989079349,
      "segmentation": [],
      "iscrowd": 0
    },
    {
      "id": 2961304473,
      "image_id": 278,
      "category_id": 0,
      "bbox": [
        160.00185599999998,
        1276.000992,
        280.998144,
        206.00092800000002
      ],
      "area": 57885.87843027764,
      "segmentation": [],
      "iscrowd": 0
    },
    {
      "id": 2621102473,
      "image_id": 278,
      "category_id": 0,
      "bbox": [
        499.00233599999996,
        0.9994319999999923,
        201.999168,
        123.00120000000001
      ],
      "area": 24846.140063001603,
      "segmentation": [],
      "iscrowd": 0
    },
    {
      "id": 1381211473,
      "image_id": 278,
      "category_id": 0,
      "bbox": [
        1181.998944,
        271.00029600000005,
        193.99967999999998,
        231.000336
      ],
      "area": 44813.99126389248,
      "segmentation": [],
      "iscrowd": 0
    },
    {
      "id": 3864918473,
      "image_id": 278,
      "category_id": 0,
      "bbox": [
        165.999456,
        238.99881600000003,
        196.99948799999999,
        154.000224
      ],
      "area": 30337.96527988531,
      "segmentation": [],
      "iscrowd": 0
    },
    {
      "id": 9005570473,
      "image_id": 278,
      "category_id": 1,
      "bbox": [
        2903.9996159999996,
        1178.000712,
        397.99872000000005,
        332.99985599999997
      ],
      "area": 132533.51644818432,
      "segmentation": [],
      "iscrowd": 0
    },
    {
      "id": 4123926473,
      "image_id": 278,
      "category_id": 1,
      "bbox": [
        2948.000832,
        654.0004799999999,
        268.998912,
        255.999744
      ],
      "area": 68863.65260827853,
      "segmentation": [],
      "iscrowd": 0
    },
    {
      "id": 1131536473,
      "image_id": 278,
      "category_id": 0,
      "bbox": [
        2672.002368,
        1416.000096,
        282.998016,
        261.00144
      ],
      "area": 73862.88969314304,
      "segmentation": [],
      "iscrowd": 0
    },
    {
      "id": 4300922473,
      "image_id": 278,
      "category_id": 0,
      "bbox": [
        1443.998304,
        614.00052,
        308.000448,
        280.99915200000004
      ],
      "area": 86547.86470362011,
      "segmentation": [],
      "iscrowd": 0
    },
    {
      "id": 5982512473,
      "image_id": 278,
      "category_id": 1,
      "bbox": [
        3300.002496,
        1450.00044,
        403.998336,
        411.000912
      ],
      "area": 166043.68454248243,
      "segmentation": [],
      "iscrowd": 0
    },
    {
      "id": 8557445473,
      "image_id": 278,
      "category_id": 0,
      "bbox": [
        2918.9986559999998,
        1902.998664,
        646.998912,
        551.0000160000001
      ],
      "area": 356496.41086398263,
      "segmentation": [],
      "iscrowd": 0
    },
    {
      "id": 7486037473,
      "image_id": 278,
      "category_id": 0,
      "bbox": [
        2997.999648,
        2468.001312,
        669.001536,
        552.99888
      ],
      "area": 369957.10012627963,
      "segmentation": [],
      "iscrowd": 0
    },
    {
      "id": 6080143473,
      "image_id": 278,
      "category_id": 0,
      "bbox": [
        2127.99888,
        521.0004240000001,
        543.001536,
        504.001008
      ],
      "area": 273673.3214895483,
      "segmentation": [],
      "iscrowd": 0
    },
    {
      "id": 8594368473,
      "image_id": 278,
      "category_id": 0,
      "bbox": [
        2682.999648,
        913.001544,
        415.001664,
        411.998832
      ],
      "area": 170980.20084605645,
      "segmentation": [],
      "iscrowd": 0
    },
    {
      "id": 9563257473,
      "image_id": 278,
      "category_id": 0,
      "bbox": [
        1757.0004480000002,
        128.999304,
        621.0005759999999,
        594.9992159999999
      ],
      "area": 369494.85585554835,
      "segmentation": [],
      "iscrowd": 0
    },
    {
      "id": 8649515473,
      "image_id": 278,
      "category_id": 0,
      "bbox": [
        2139.000192,
        1710.000936,
        635.999616,
        646.99992
      ],
      "area": 411491.7006720307,
      "segmentation": [],
      "iscrowd": 0
    },
    {
      "id": 7602222473,
      "image_id": 278,
      "category_id": 0,
      "bbox": [
        2272.9976640000004,
        2358.0002879999997,
        663.00192,
        651.000672
      ],
      "area": 431614.6954572903,
      "segmentation": [],
      "iscrowd": 0
    }
  ],
  "categories": [
    {
      "id": 0,
      "name": "tomato_plant",
      "supercategory": "plant"
    },
    {
      "id": 1,
      "name": "tomato_fruit",
      "supercategory": "fruit"
    }
  ]
}