{
  "info": {
    "description": "Tomato Plant Dataset - Images of tomato plants with bounding box annotations",
    "version": "1.0",
    "year": 2024,
    "contributor": "Tomato Plant Research",
    "date_created": "2025/04/12",
    "url": ""
  },
  "images": [
    {
      "id": 492,
      "license": 1,
      "file_name": "0491.JPG",
      "height": 3024,
      "width": 4032,
      "date_captured": "2025-04-12"
    }
  ],
  "annotations": [
    {
      "id": 1292678478,
      "image_id": 492,
      "category_id": 1,
      "bbox": [
        22.000608,
        1096.9983359999999,
        160.001856,
        142.000992
      ],
      "area": 22720.42227384115,
      "segmentation": [],
      "iscrowd": 0
    },
    {
      "id": 2451691478,
      "image_id": 492,
      "category_id": 0,
      "bbox": [
        9.997343999999982,
        415.000152,
        288.001728,
        423.00014400000003
      ],
      "area": 121824.77241624884,
      "segmentation": [],
      "iscrowd": 0
    },
    {
      "id": 7851919478,
      "image_id": 492,
      "category_id": 0,
      "bbox": [
        1186.0007040000003,
        291.998952,
        505.999872,
        434.99937600000004
      ],
      "area": 220109.62857607988,
      "segmentation": [],
      "iscrowd": 0
    },
    {
      "id": 3724388478,
      "image_id": 492,
      "category_id": 1,
      "bbox": [
        822.999744,
        1.0009439999999938,
        381.999744,
        305.00064000000003
      ],
      "area": 116510.16639983618,
      "segmentation": [],
      "iscrowd": 0
    },
    {
      "id": 8101554478,
      "image_id": 492,
      "category_id": 0,
      "bbox": [
        1637.997984,
        420.001848,
        300.00096,
        344.999088
      ],
      "area": 103500.05759912448,
      "segmentation": [],
      "iscrowd": 0
    },
    {
      "id": 5256631478,
      "image_id": 492,
      "category_id": 1,
      "bbox": [
        81.000864,
        1111.000968,
        166.001472,
        149.999472
      ],
      "area": 24900.133151222784,
      "segmentation": [],
      "iscrowd": 0
    },
    {
      "id": 4543991478,
      "image_id": 492,
      "category_id": 1,
      "bbox": [
        3577.000896,
        851.000472,
        255.99974400000002,
        184.999248
      ],
      "area": 47359.760128192516,
      "segmentation": [],
      "iscrowd": 0
    },
    {
      "id": 8833835478,
      "image_id": 492,
      "category_id": 1,
      "bbox": [
        3912.9995519999998,
        1065.001392,
        117.000576,
        346.00003200000003
      ],
      "area": 40482.20304001844,
      "segmentation": [],
      "iscrowd": 0
    },
    {
      "id": 6183162478,
      "image_id": 492,
      "category_id": 1,
      "bbox": [
        3548.9986559999998,
        1089.0013680000002,
        369.000576,
        283.99896
      ],
      "area": 104795.77982340097,
      "segmentation": [],
      "iscrowd": 0
    },
    {
      "id": 8504933478,
      "image_id": 492,
      "category_id": 0,
      "bbox": [
        378.999936,
        10.000367999999993,
        352.001664,
        305.99856
      ],
      "area": 107712.00230160385,
      "segmentation": [],
      "iscrowd": 0
    },
    {
      "id": 5099215478,
      "image_id": 492,
      "category_id": 1,
      "bbox": [
        2733.00048,
        411.000912,
        210.998592,
        238.00089599999998
      ],
      "area": 50217.85395073843,
      "segmentation": [],
      "iscrowd": 0
    },
    {
      "id": 2406436478,
      "image_id": 492,
      "category_id": 0,
      "bbox": [
        2545.0004160000003,
        1868.0004,
        673.0012800000001,
        465.00048
      ],
      "area": 312945.9182406144,
      "segmentation": [],
      "iscrowd": 0
    },
    {
      "id": 2883501478,
      "image_id": 492,
      "category_id": 1,
      "bbox": [
        1692.998496,
        2.000375999999986,
        560.000448,
        309.99931200000003
      ],
      "area": 173599.7535996918,
      "segmentation": [],
      "iscrowd": 0
    },
    {
      "id": 5708127478,
      "image_id": 492,
      "category_id": 1,
      "bbox": [
        1784.9986560000002,
        139.00118400000002,
        641.999232,
        584.9988480000001
      ],
      "area": 375568.8111368848,
      "segmentation": [],
      "iscrowd": 0
    },
    {
      "id": 1503759478,
      "image_id": 492,
      "category_id": 0,
      "bbox": [
        2977.998912,
        1510.001136,
        873.0005759999999,
        811.000512
      ],
      "area": 708003.9141122948,
      "segmentation": [],
      "iscrowd": 0
    },
    {
      "id": 3744223478,
      "image_id": 492,
      "category_id": 1,
      "bbox": [
        2965.9996799999994,
        342.00079200000005,
        272.99865600000004,
        277.001424
      ],
      "area": 75621.01646208615,
      "segmentation": [],
      "iscrowd": 0
    },
    {
      "id": 5874059478,
      "image_id": 492,
      "category_id": 0,
      "bbox": [
        2413.9987200000005,
        1315.0000079999998,
        644.99904,
        603.00072
      ],
      "area": 388934.8855193088,
      "segmentation": [],
      "iscrowd": 0
    },
    {
      "id": 8086261478,
      "image_id": 492,
      "category_id": 0,
      "bbox": [
        1850.000544,
        1884.000384,
        669.001536,
        660.000096
      ],
      "area": 441541.0779841474,
      "segmentation": [],
      "iscrowd": 0
    },
    {
      "id": 6257087478,
      "image_id": 492,
      "category_id": 1,
      "bbox": [
        993.9988800000001,
        1978.999344,
        290.0016,
        238.99881599999998
      ],
      "area": 69310.03903810559,
      "segmentation": [],
      "iscrowd": 0
    },
    {
      "id": 2868073478,
      "image_id": 492,
      "category_id": 1,
      "bbox": [
        1706.999616,
        228.99996000000002,
        235.001088,
        286.99876800000004
      ],
      "area": 67445.0227346596,
      "segmentation": [],
      "iscrowd": 0
    }
  ],
  "categories": [
    {
      "id": 0,
      "name": "tomato_plant",
      "supercategory": "plant"
    },
    {
      "id": 1,
      "name": "tomato_fruit",
      "supercategory": "fruit"
    }
  ]
}