<?xml version='1.0' encoding='UTF-8'?>
<annotation>
	<folder>Images</folder>
	<filename>0203.JPG</filename>
	<path>Images\0203.JPG</path>
	<source>
		<database>Unknown</database>
	</source>
	<size>
		<width>6000</width>
		<height>4000</height>
		<depth>3</depth>
	</size>
	<segmented>0</segmented>
	<object>
		<name>green</name>
		<pose>Unspecified</pose>
		<truncated>0</truncated>
		<difficult>0</difficult>
		<bndbox>
			<xmin>769</xmin>
			<ymin>1517</ymin>
			<xmax>1198</xmax>
			<ymax>1850</ymax>
		</bndbox>
	</object>
	<object>
		<name>green</name>
		<pose>Unspecified</pose>
		<truncated>0</truncated>
		<difficult>0</difficult>
		<bndbox>
			<xmin>1448</xmin>
			<ymin>2812</ymin>
			<xmax>1956</xmax>
			<ymax>3342</ymax>
		</bndbox>
	</object>
	<object>
		<name>green</name>
		<pose>Unspecified</pose>
		<truncated>0</truncated>
		<difficult>0</difficult>
		<bndbox>
			<xmin>2106</xmin>
			<ymin>2433</ymin>
			<xmax>2719</xmax>
			<ymax>2979</ymax>
		</bndbox>
	</object>
	<object>
		<name>green</name>
		<pose>Unspecified</pose>
		<truncated>0</truncated>
		<difficult>0</difficult>
		<bndbox>
			<xmin>2740</xmin>
			<ymin>987</ymin>
			<xmax>3148</xmax>
			<ymax>1304</ymax>
		</bndbox>
	</object>
	<object>
		<name>green</name>
		<pose>Unspecified</pose>
		<truncated>0</truncated>
		<difficult>0</difficult>
		<bndbox>
			<xmin>3760</xmin>
			<ymin>1187</ymin>
			<xmax>4135</xmax>
			<ymax>1542</ymax>
		</bndbox>
	</object>
	<object>
		<name>green</name>
		<pose>Unspecified</pose>
		<truncated>0</truncated>
		<difficult>1</difficult>
		<bndbox>
			<xmin>3648</xmin>
			<ymin>512</ymin>
			<xmax>4015</xmax>
			<ymax>771</ymax>
		</bndbox>
	</object>
	<object>
		<name>green</name>
		<pose>Unspecified</pose>
		<truncated>0</truncated>
		<difficult>0</difficult>
		<bndbox>
			<xmin>3010</xmin>
			<ymin>1921</ymin>
			<xmax>3523</xmax>
			<ymax>2417</ymax>
		</bndbox>
	</object>
	<object>
		<name>green</name>
		<pose>Unspecified</pose>
		<truncated>0</truncated>
		<difficult>0</difficult>
		<bndbox>
			<xmin>2785</xmin>
			<ymin>2617</ymin>
			<xmax>3252</xmax>
			<ymax>3092</ymax>
		</bndbox>
	</object>
	<object>
		<name>green</name>
		<pose>Unspecified</pose>
		<truncated>0</truncated>
		<difficult>0</difficult>
		<bndbox>
			<xmin>3252</xmin>
			<ymin>2721</ymin>
			<xmax>3577</xmax>
			<ymax>3000</ymax>
		</bndbox>
	</object>
	<object>
		<name>green</name>
		<pose>Unspecified</pose>
		<truncated>0</truncated>
		<difficult>0</difficult>
		<bndbox>
			<xmin>3102</xmin>
			<ymin>3037</ymin>
			<xmax>3694</xmax>
			<ymax>3592</ymax>
		</bndbox>
	</object>
	<object>
		<name>green</name>
		<pose>Unspecified</pose>
		<truncated>0</truncated>
		<difficult>0</difficult>
		<bndbox>
			<xmin>3581</xmin>
			<ymin>3346</ymin>
			<xmax>4014</xmax>
			<ymax>3750</ymax>
		</bndbox>
	</object>
	<object>
		<name>green</name>
		<pose>Unspecified</pose>
		<truncated>0</truncated>
		<difficult>0</difficult>
		<bndbox>
			<xmin>3135</xmin>
			<ymin>1596</ymin>
			<xmax>3556</xmax>
			<ymax>1896</ymax>
		</bndbox>
	</object>
	<object>
		<name>green</name>
		<pose>Unspecified</pose>
		<truncated>0</truncated>
		<difficult>1</difficult>
		<bndbox>
			<xmin>1052</xmin>
			<ymin>1279</ymin>
			<xmax>1419</xmax>
			<ymax>1537</ymax>
		</bndbox>
	</object>
	<object>
		<name>green</name>
		<pose>Unspecified</pose>
		<truncated>0</truncated>
		<difficult>0</difficult>
		<bndbox>
			<xmin>3565</xmin>
			<ymin>1725</ymin>
			<xmax>4006</xmax>
			<ymax>2046</ymax>
		</bndbox>
	</object>
	<object>
		<name>green</name>
		<pose>Unspecified</pose>
		<truncated>0</truncated>
		<difficult>1</difficult>
		<bndbox>
			<xmin>3673</xmin>
			<ymin>2337</ymin>
			<xmax>3931</xmax>
			<ymax>2550</ymax>
		</bndbox>
	</object>
	<object>
		<name>green</name>
		<pose>Unspecified</pose>
		<truncated>0</truncated>
		<difficult>0</difficult>
		<bndbox>
			<xmin>4523</xmin>
			<ymin>2183</ymin>
			<xmax>4960</xmax>
			<ymax>2583</ymax>
		</bndbox>
	</object>
	<object>
		<name>green</name>
		<pose>Unspecified</pose>
		<truncated>0</truncated>
		<difficult>0</difficult>
		<bndbox>
			<xmin>5290</xmin>
			<ymin>1662</ymin>
			<xmax>5710</xmax>
			<ymax>2054</ymax>
		</bndbox>
	</object>
	<object>
		<name>green</name>
		<pose>Unspecified</pose>
		<truncated>0</truncated>
		<difficult>0</difficult>
		<bndbox>
			<xmin>5290</xmin>
			<ymin>1258</ymin>
			<xmax>5615</xmax>
			<ymax>1533</ymax>
		</bndbox>
	</object>
	<object>
		<name>green</name>
		<pose>Unspecified</pose>
		<truncated>0</truncated>
		<difficult>0</difficult>
		<bndbox>
			<xmin>5835</xmin>
			<ymin>2167</ymin>
			<xmax>5998</xmax>
			<ymax>2462</ymax>
		</bndbox>
	</object>
	<object>
		<name>green</name>
		<pose>Unspecified</pose>
		<truncated>0</truncated>
		<difficult>1</difficult>
		<bndbox>
			<xmin>4915</xmin>
			<ymin>2700</ymin>
			<xmax>5173</xmax>
			<ymax>3004</ymax>
		</bndbox>
	</object>
	<object>
		<name>green</name>
		<pose>Unspecified</pose>
		<truncated>0</truncated>
		<difficult>1</difficult>
		<bndbox>
			<xmin>4835</xmin>
			<ymin>1546</ymin>
			<xmax>5231</xmax>
			<ymax>1883</ymax>
		</bndbox>
	</object>
	<object>
		<name>green</name>
		<pose>Unspecified</pose>
		<truncated>0</truncated>
		<difficult>1</difficult>
		<bndbox>
			<xmin>3973</xmin>
			<ymin>1675</ymin>
			<xmax>4206</xmax>
			<ymax>1962</ymax>
		</bndbox>
	</object>
	<object>
		<name>green</name>
		<pose>Unspecified</pose>
		<truncated>0</truncated>
		<difficult>1</difficult>
		<bndbox>
			<xmin>5248</xmin>
			<ymin>367</ymin>
			<xmax>5527</xmax>
			<ymax>704</ymax>
		</bndbox>
	</object>
</annotation>
