<?xml version='1.0' encoding='UTF-8'?>
<annotation>
	<folder>Images</folder>
	<filename>0142.JPG</filename>
	<path>Images\0142.JPG</path>
	<source>
		<database>Unknown</database>
	</source>
	<size>
		<width>6000</width>
		<height>4000</height>
		<depth>3</depth>
	</size>
	<segmented>0</segmented>
	<object>
		<name>green</name>
		<pose>Unspecified</pose>
		<truncated>0</truncated>
		<difficult>0</difficult>
		<bndbox>
			<xmin>1294</xmin>
			<ymin>2673</ymin>
			<xmax>2194</xmax>
			<ymax>3573</ymax>
		</bndbox>
	</object>
	<object>
		<name>green</name>
		<pose>Unspecified</pose>
		<truncated>0</truncated>
		<difficult>0</difficult>
		<bndbox>
			<xmin>1184</xmin>
			<ymin>995</ymin>
			<xmax>2180</xmax>
			<ymax>1991</ymax>
		</bndbox>
	</object>
	<object>
		<name>green</name>
		<pose>Unspecified</pose>
		<truncated>0</truncated>
		<difficult>0</difficult>
		<bndbox>
			<xmin>2489</xmin>
			<ymin>778</ymin>
			<xmax>3337</xmax>
			<ymax>1626</ymax>
		</bndbox>
	</object>
	<object>
		<name>green</name>
		<pose>Unspecified</pose>
		<truncated>0</truncated>
		<difficult>0</difficult>
		<bndbox>
			<xmin>4876</xmin>
			<ymin>1651</ymin>
			<xmax>5216</xmax>
			<ymax>1928</ymax>
		</bndbox>
	</object>
	<object>
		<name>green</name>
		<pose>Unspecified</pose>
		<truncated>0</truncated>
		<difficult>0</difficult>
		<bndbox>
			<xmin>4668</xmin>
			<ymin>1056</ymin>
			<xmax>4951</xmax>
			<ymax>1351</ymax>
		</bndbox>
	</object>
	<object>
		<name>green</name>
		<pose>Unspecified</pose>
		<truncated>0</truncated>
		<difficult>0</difficult>
		<bndbox>
			<xmin>4653</xmin>
			<ymin>2253</ymin>
			<xmax>4889</xmax>
			<ymax>2518</ymax>
		</bndbox>
	</object>
</annotation>
