<?xml version='1.0' encoding='UTF-8'?>
<annotation>
	<folder>Images</folder>
	<filename>0187.JPG</filename>
	<path>Images\0187.JPG</path>
	<source>
		<database>Unknown</database>
	</source>
	<size>
		<width>6000</width>
		<height>4000</height>
		<depth>3</depth>
	</size>
	<segmented>0</segmented>
	<object>
		<name>green</name>
		<pose>Unspecified</pose>
		<truncated>0</truncated>
		<difficult>0</difficult>
		<bndbox>
			<xmin>85</xmin>
			<ymin>4</ymin>
			<xmax>789</xmax>
			<ymax>617</ymax>
		</bndbox>
	</object>
	<object>
		<name>green</name>
		<pose>Unspecified</pose>
		<truncated>0</truncated>
		<difficult>0</difficult>
		<bndbox>
			<xmin>59</xmin>
			<ymin>596</ymin>
			<xmax>515</xmax>
			<ymax>1117</ymax>
		</bndbox>
	</object>
	<object>
		<name>green</name>
		<pose>Unspecified</pose>
		<truncated>0</truncated>
		<difficult>0</difficult>
		<bndbox>
			<xmin>1785</xmin>
			<ymin>1882</ymin>
			<xmax>2889</xmax>
			<ymax>3030</ymax>
		</bndbox>
	</object>
	<object>
		<name>green</name>
		<pose>Unspecified</pose>
		<truncated>0</truncated>
		<difficult>0</difficult>
		<bndbox>
			<xmin>3237</xmin>
			<ymin>1378</ymin>
			<xmax>4259</xmax>
			<ymax>2439</ymax>
		</bndbox>
	</object>
	<object>
		<name>green</name>
		<pose>Unspecified</pose>
		<truncated>0</truncated>
		<difficult>0</difficult>
		<bndbox>
			<xmin>2859</xmin>
			<ymin>2356</ymin>
			<xmax>3785</xmax>
			<ymax>3296</ymax>
		</bndbox>
	</object>
	<object>
		<name>green</name>
		<pose>Unspecified</pose>
		<truncated>0</truncated>
		<difficult>0</difficult>
		<bndbox>
			<xmin>2950</xmin>
			<ymin>2935</ymin>
			<xmax>3820</xmax>
			<ymax>3796</ymax>
		</bndbox>
	</object>
	<object>
		<name>green</name>
		<pose>Unspecified</pose>
		<truncated>0</truncated>
		<difficult>0</difficult>
		<bndbox>
			<xmin>2059</xmin>
			<ymin>2396</ymin>
			<xmax>2854</xmax>
			<ymax>3256</ymax>
		</bndbox>
	</object>
</annotation>
