<?xml version='1.0' encoding='UTF-8'?>
<annotation>
	<folder>Images</folder>
	<filename>0344.JPG</filename>
	<path>Images\0344.JPG</path>
	<source>
		<database>Unknown</database>
	</source>
	<size>
		<width>6000</width>
		<height>4000</height>
		<depth>3</depth>
	</size>
	<segmented>0</segmented>
	<object>
		<name>green</name>
		<pose>Unspecified</pose>
		<truncated>0</truncated>
		<difficult>0</difficult>
		<bndbox>
			<xmin>4150</xmin>
			<ymin>2696</ymin>
			<xmax>4921</xmax>
			<ymax>3379</ymax>
		</bndbox>
	</object>
	<object>
		<name>green</name>
		<pose>Unspecified</pose>
		<truncated>0</truncated>
		<difficult>0</difficult>
		<bndbox>
			<xmin>4575</xmin>
			<ymin>1875</ymin>
			<xmax>5242</xmax>
			<ymax>2471</ymax>
		</bndbox>
	</object>
	<object>
		<name>green</name>
		<pose>Unspecified</pose>
		<truncated>0</truncated>
		<difficult>0</difficult>
		<bndbox>
			<xmin>3533</xmin>
			<ymin>2187</ymin>
			<xmax>4279</xmax>
			<ymax>2925</ymax>
		</bndbox>
	</object>
	<object>
		<name>green</name>
		<pose>Unspecified</pose>
		<truncated>0</truncated>
		<difficult>0</difficult>
		<bndbox>
			<xmin>3233</xmin>
			<ymin>2529</ymin>
			<xmax>3737</xmax>
			<ymax>3058</ymax>
		</bndbox>
	</object>
	<object>
		<name>green</name>
		<pose>Unspecified</pose>
		<truncated>0</truncated>
		<difficult>0</difficult>
		<bndbox>
			<xmin>3058</xmin>
			<ymin>833</ymin>
			<xmax>3821</xmax>
			<ymax>1512</ymax>
		</bndbox>
	</object>
	<object>
		<name>green</name>
		<pose>Unspecified</pose>
		<truncated>0</truncated>
		<difficult>1</difficult>
		<bndbox>
			<xmin>2621</xmin>
			<ymin>1071</ymin>
			<xmax>3021</xmax>
			<ymax>1550</ymax>
		</bndbox>
	</object>
	<object>
		<name>green</name>
		<pose>Unspecified</pose>
		<truncated>0</truncated>
		<difficult>0</difficult>
		<bndbox>
			<xmin>992</xmin>
			<ymin>979</ymin>
			<xmax>1592</xmax>
			<ymax>1604</ymax>
		</bndbox>
	</object>
	<object>
		<name>green</name>
		<pose>Unspecified</pose>
		<truncated>0</truncated>
		<difficult>0</difficult>
		<bndbox>
			<xmin>1629</xmin>
			<ymin>1183</ymin>
			<xmax>2275</xmax>
			<ymax>1758</ymax>
		</bndbox>
	</object>
	<object>
		<name>green</name>
		<pose>Unspecified</pose>
		<truncated>0</truncated>
		<difficult>1</difficult>
		<bndbox>
			<xmin>2142</xmin>
			<ymin>779</ymin>
			<xmax>2750</xmax>
			<ymax>1404</ymax>
		</bndbox>
	</object>
</annotation>
